[{"lat_center":52.6,"lon_center":4.8,"detection_count":288,"mean_confidence":0.7645863608146707},{"lat_center":51.7,"lon_center":4.3,"detection_count":205,"mean_confidence":0.8137533568754429},{"lat_center":52.4,"lon_center":6.4,"detection_count":79,"mean_confidence":0.6008307009558135},{"lat_center":51.9,"lon_center":4.1,"detection_count":43,"mean_confidence":0.7437660666399224},{"lat_center":51.9,"lon_center":4.3,"detection_count":30,"mean_confidence":0.8003730556042988},{"lat_center":52.7,"lon_center":4.7,"detection_count":28,"mean_confidence":0.6906142742787089},{"lat_center":52.0,"lon_center":4.7,"detection_count":26,"mean_confidence":0.8018887524421399},{"lat_center":52.0,"lon_center":6.6,"detection_count":25,"mean_confidence":0.5977535605430603},{"lat_center":52.6,"lon_center":4.7,"detection_count":20,"mean_confidence":0.549981938302517},{"lat_center":51.9,"lon_center":5.2,"detection_count":19,"mean_confidence":0.564668302473269},{"lat_center":52.7,"lon_center":4.8,"detection_count":19,"mean_confidence":0.5728085511609128},{"lat_center":53.2,"lon_center":6.0,"detection_count":18,"mean_confidence":0.792235854599211},{"lat_center":51.0,"lon_center":4.2,"detection_count":17,"mean_confidence":0.6810037213213304},{"lat_center":52.0,"lon_center":5.2,"detection_count":15,"mean_confidence":0.7313876271247863},{"lat_center":50.9,"lon_center":4.7,"detection_count":13,"mean_confidence":0.7888136506080627},{"lat_center":52.3,"lon_center":5.3,"detection_count":12,"mean_confidence":0.7994896928707759},{"lat_center":52.5,"lon_center":6.4,"detection_count":12,"mean_confidence":0.6148282960057259},{"lat_center":51.2,"lon_center":4.0,"detection_count":10,"mean_confidence":0.5218518674373627},{"lat_center":52.0,"lon_center":6.3,"detection_count":10,"mean_confidence":0.593951964378357},{"lat_center":50.9,"lon_center":6.7,"detection_count":9,"mean_confidence":0.7844444444444444},{"lat_center":52.0,"lon_center":4.2,"detection_count":8,"mean_confidence":0.6880693137645721},{"lat_center":52.5,"lon_center":4.9,"detection_count":8,"mean_confidence":0.670551523566246},{"lat_center":51.2,"lon_center":3.9,"detection_count":7,"mean_confidence":0.5106058078152793},{"lat_center":51.5,"lon_center":4.9,"detection_count":6,"mean_confidence":0.537348876396815},{"lat_center":51.8,"lon_center":4.7,"detection_count":6,"mean_confidence":0.6251268088817596},{"lat_center":52.1,"lon_center":5.2,"detection_count":6,"mean_confidence":0.4922005583842595},{"lat_center":52.1,"lon_center":6.5,"detection_count":6,"mean_confidence":0.7350036899248759},{"lat_center":52.8,"lon_center":6.1,"detection_count":6,"mean_confidence":0.5596222380797068},{"lat_center":52.1,"lon_center":6.4,"detection_count":5,"mean_confidence":0.6962160110473633},{"lat_center":51.9,"lon_center":5.8,"detection_count":4,"mean_confidence":0.5684996843338013},{"lat_center":52.0,"lon_center":4.5,"detection_count":4,"mean_confidence":0.5969031453132629},{"lat_center":52.1,"lon_center":4.3,"detection_count":4,"mean_confidence":0.6793915033340454},{"lat_center":52.9,"lon_center":6.0,"detection_count":4,"mean_confidence":0.6887241303920746},{"lat_center":51.1,"lon_center":4.5,"detection_count":3,"mean_confidence":0.6539787451426188},{"lat_center":51.4,"lon_center":6.8,"detection_count":3,"mean_confidence":0.7666666666666666},{"lat_center":51.5,"lon_center":4.5,"detection_count":3,"mean_confidence":0.6095616022745768},{"lat_center":51.9,"lon_center":6.7,"detection_count":3,"mean_confidence":0.685809592405955},{"lat_center":52.4,"lon_center":4.6,"detection_count":3,"mean_confidence":0.7490756313006083},{"lat_center":52.4,"lon_center":4.7,"detection_count":3,"mean_confidence":0.45867009957631427},{"lat_center":52.9,"lon_center":5.5,"detection_count":3,"mean_confidence":0.7103836536407471},{"lat_center":51.4,"lon_center":5.6,"detection_count":2,"mean_confidence":0.614984929561615},{"lat_center":51.4,"lon_center":6.9,"detection_count":2,"mean_confidence":0.5579763054847717},{"lat_center":51.5,"lon_center":5.6,"detection_count":2,"mean_confidence":0.8515196740627289},{"lat_center":51.7,"lon_center":4.5,"detection_count":2,"mean_confidence":0.6690095961093903},{"lat_center":51.9,"lon_center":4.9,"detection_count":2,"mean_confidence":0.8835948705673218},{"lat_center":52.0,"lon_center":4.6,"detection_count":2,"mean_confidence":0.7423436343669891},{"lat_center":52.0,"lon_center":5.6,"detection_count":2,"mean_confidence":0.4825035482645035},{"lat_center":52.3,"lon_center":5.2,"detection_count":2,"mean_confidence":0.6738948822021484},{"lat_center":53.3,"lon_center":5.0,"detection_count":2,"mean_confidence":0.6364910900592804},{"lat_center":53.3,"lon_center":6.1,"detection_count":2,"mean_confidence":0.6598750948905945},{"lat_center":50.8,"lon_center":3.9,"detection_count":1,"mean_confidence":0.7263},{"lat_center":50.9,"lon_center":3.5,"detection_count":1,"mean_confidence":0.6726714372634888},{"lat_center":50.9,"lon_center":4.8,"detection_count":1,"mean_confidence":0.758959949016571},{"lat_center":51.0,"lon_center":3.7,"detection_count":1,"mean_confidence":0.6673619747161865},{"lat_center":51.1,"lon_center":5.3,"detection_count":1,"mean_confidence":0.5037923455238342},{"lat_center":51.2,"lon_center":4.2,"detection_count":1,"mean_confidence":0.5618442893028259},{"lat_center":51.2,"lon_center":6.4,"detection_count":1,"mean_confidence":0.7242},{"lat_center":51.3,"lon_center":4.5,"detection_count":1,"mean_confidence":0.8639415502548218},{"lat_center":51.6,"lon_center":4.7,"detection_count":1,"mean_confidence":0.663522481918335},{"lat_center":51.6,"lon_center":5.2,"detection_count":1,"mean_confidence":0.7612},{"lat_center":51.7,"lon_center":3.9,"detection_count":1,"mean_confidence":0.5938858389854431},{"lat_center":51.8,"lon_center":5.9,"detection_count":1,"mean_confidence":0.5412473082542419},{"lat_center":51.8,"lon_center":6.7,"detection_count":1,"mean_confidence":0.7619},{"lat_center":51.8,"lon_center":7.2,"detection_count":1,"mean_confidence":0.83},{"lat_center":51.9,"lon_center":5.9,"detection_count":1,"mean_confidence":0.6326785087585449},{"lat_center":52.0,"lon_center":4.3,"detection_count":1,"mean_confidence":0.7596},{"lat_center":52.0,"lon_center":6.7,"detection_count":1,"mean_confidence":0.6757457852363586},{"lat_center":52.1,"lon_center":4.5,"detection_count":1,"mean_confidence":0.7633},{"lat_center":52.1,"lon_center":5.1,"detection_count":1,"mean_confidence":0.7079},{"lat_center":52.1,"lon_center":5.5,"detection_count":1,"mean_confidence":0.8},{"lat_center":52.1,"lon_center":6.2,"detection_count":1,"mean_confidence":0.518295168876648},{"lat_center":52.2,"lon_center":4.4,"detection_count":1,"mean_confidence":0.9505517482757568},{"lat_center":52.2,"lon_center":5.4,"detection_count":1,"mean_confidence":0.5630342364311218},{"lat_center":52.2,"lon_center":5.8,"detection_count":1,"mean_confidence":0.7889},{"lat_center":52.3,"lon_center":4.7,"detection_count":1,"mean_confidence":0.557269275188446},{"lat_center":52.3,"lon_center":6.3,"detection_count":1,"mean_confidence":0.4850524067878723},{"lat_center":52.3,"lon_center":6.8,"detection_count":1,"mean_confidence":0.8206},{"lat_center":52.4,"lon_center":6.5,"detection_count":1,"mean_confidence":0.764},{"lat_center":52.4,"lon_center":7.1,"detection_count":1,"mean_confidence":0.9},{"lat_center":53.3,"lon_center":5.1,"detection_count":1,"mean_confidence":0.5697703957557678}]