[{"lat_center":51.4,"lon_center":4.5,"detection_count":5218,"mean_confidence":0.835277596005264},{"lat_center":51.8,"lon_center":6.1,"detection_count":4357,"mean_confidence":0.9072028265815825},{"lat_center":52.1,"lon_center":5.2,"detection_count":3964,"mean_confidence":0.753623461680215},{"lat_center":52.5,"lon_center":6.9,"detection_count":2205,"mean_confidence":0.7765829164424991},{"lat_center":52.0,"lon_center":5.8,"detection_count":2008,"mean_confidence":0.6742856671813237},{"lat_center":52.2,"lon_center":6.1,"detection_count":1832,"mean_confidence":0.7822676640345541},{"lat_center":52.4,"lon_center":7.1,"detection_count":1611,"mean_confidence":0.8534823091247673},{"lat_center":52.1,"lon_center":5.3,"detection_count":1555,"mean_confidence":0.9331936490880715},{"lat_center":51.8,"lon_center":5.9,"detection_count":1208,"mean_confidence":0.7074825367607818},{"lat_center":51.1,"lon_center":7.0,"detection_count":1206,"mean_confidence":0.8474850746268657},{"lat_center":52.4,"lon_center":6.4,"detection_count":1155,"mean_confidence":0.5828078734410274},{"lat_center":51.6,"lon_center":4.7,"detection_count":1090,"mean_confidence":0.811098142446728},{"lat_center":52.4,"lon_center":6.5,"detection_count":1069,"mean_confidence":0.648851617078674},{"lat_center":51.0,"lon_center":3.9,"detection_count":1058,"mean_confidence":0.7112608090014899},{"lat_center":50.9,"lon_center":6.7,"detection_count":1051,"mean_confidence":0.8620932445290199},{"lat_center":52.3,"lon_center":7.1,"detection_count":968,"mean_confidence":0.8505268595041322},{"lat_center":52.1,"lon_center":5.6,"detection_count":918,"mean_confidence":0.7972099559912854},{"lat_center":51.4,"lon_center":6.9,"detection_count":870,"mean_confidence":0.7360788830395403},{"lat_center":51.5,"lon_center":5.5,"detection_count":537,"mean_confidence":0.8725532588454377},{"lat_center":52.7,"lon_center":4.7,"detection_count":536,"mean_confidence":0.6528387554526329},{"lat_center":51.0,"lon_center":4.2,"detection_count":514,"mean_confidence":0.6748427722008775},{"lat_center":52.0,"lon_center":6.6,"detection_count":496,"mean_confidence":0.5138785045353635},{"lat_center":51.5,"lon_center":4.9,"detection_count":488,"mean_confidence":0.7619892918184156},{"lat_center":51.1,"lon_center":4.5,"detection_count":476,"mean_confidence":0.7346379529027378},{"lat_center":52.1,"lon_center":5.4,"detection_count":446,"mean_confidence":0.8154730941704036},{"lat_center":52.0,"lon_center":5.7,"detection_count":430,"mean_confidence":0.8207988679191678},{"lat_center":51.5,"lon_center":4.5,"detection_count":426,"mean_confidence":0.7230050373525126},{"lat_center":52.2,"lon_center":5.1,"detection_count":417,"mean_confidence":0.8156525179856114},{"lat_center":52.4,"lon_center":4.9,"detection_count":416,"mean_confidence":0.8947550569048295},{"lat_center":51.3,"lon_center":4.5,"detection_count":404,"mean_confidence":0.8969001831491394},{"lat_center":51.8,"lon_center":7.2,"detection_count":402,"mean_confidence":0.8386318407960199},{"lat_center":52.1,"lon_center":6.5,"detection_count":395,"mean_confidence":0.8343245489651644},{"lat_center":52.1,"lon_center":6.3,"detection_count":389,"mean_confidence":0.7405673752713633},{"lat_center":51.2,"lon_center":6.9,"detection_count":388,"mean_confidence":0.6932976245880127},{"lat_center":52.3,"lon_center":5.3,"detection_count":387,"mean_confidence":0.8004167019003738},{"lat_center":52.2,"lon_center":5.3,"detection_count":382,"mean_confidence":0.7568135480503762},{"lat_center":50.9,"lon_center":3.4,"detection_count":362,"mean_confidence":0.6714669125185487},{"lat_center":52.1,"lon_center":5.1,"detection_count":318,"mean_confidence":0.8734143575368438},{"lat_center":50.9,"lon_center":4.7,"detection_count":309,"mean_confidence":0.7929609429489062},{"lat_center":52.5,"lon_center":5.5,"detection_count":282,"mean_confidence":0.8945780491575281},{"lat_center":50.9,"lon_center":4.8,"detection_count":252,"mean_confidence":0.8290144084464937},{"lat_center":52.2,"lon_center":4.5,"detection_count":252,"mean_confidence":0.7843231915954559},{"lat_center":50.9,"lon_center":5.7,"detection_count":240,"mean_confidence":0.8291405015226204},{"lat_center":52.8,"lon_center":6.1,"detection_count":233,"mean_confidence":0.5915434520387854},{"lat_center":50.8,"lon_center":3.9,"detection_count":232,"mean_confidence":0.8581405755700736},{"lat_center":51.4,"lon_center":5.5,"detection_count":229,"mean_confidence":0.784242204443336},{"lat_center":52.9,"lon_center":6.0,"detection_count":223,"mean_confidence":0.7832288998659416},{"lat_center":50.8,"lon_center":5.7,"detection_count":221,"mean_confidence":0.8341140271493213},{"lat_center":52.6,"lon_center":4.8,"detection_count":219,"mean_confidence":0.6216475355298552},{"lat_center":51.2,"lon_center":4.9,"detection_count":199,"mean_confidence":0.7299142587724043},{"lat_center":52.6,"lon_center":4.7,"detection_count":196,"mean_confidence":0.7214407105835117},{"lat_center":52.0,"lon_center":6.7,"detection_count":191,"mean_confidence":0.5598807529941279},{"lat_center":52.4,"lon_center":6.0,"detection_count":188,"mean_confidence":0.9389138297872341},{"lat_center":52.2,"lon_center":5.7,"detection_count":181,"mean_confidence":0.6958074082327153},{"lat_center":52.0,"lon_center":6.8,"detection_count":180,"mean_confidence":0.6140303403139115},{"lat_center":51.9,"lon_center":4.1,"detection_count":175,"mean_confidence":0.5355018855844225},{"lat_center":51.1,"lon_center":5.3,"detection_count":171,"mean_confidence":0.681305346084617},{"lat_center":53.1,"lon_center":6.9,"detection_count":166,"mean_confidence":0.7866897590361446},{"lat_center":53.2,"lon_center":6.0,"detection_count":164,"mean_confidence":0.7228499036736604},{"lat_center":52.1,"lon_center":6.4,"detection_count":158,"mean_confidence":0.7603178375129458},{"lat_center":50.9,"lon_center":5.3,"detection_count":157,"mean_confidence":0.7899397782981775},{"lat_center":51.5,"lon_center":3.6,"detection_count":154,"mean_confidence":0.6220059387095562},{"lat_center":53.2,"lon_center":6.6,"detection_count":154,"mean_confidence":0.8209293490493452},{"lat_center":52.0,"lon_center":4.7,"detection_count":153,"mean_confidence":0.6507176250414132},{"lat_center":51.0,"lon_center":7.1,"detection_count":146,"mean_confidence":0.8183561643835616},{"lat_center":51.8,"lon_center":4.7,"detection_count":142,"mean_confidence":0.5755372807173662},{"lat_center":52.2,"lon_center":6.9,"detection_count":141,"mean_confidence":0.8357283687943262},{"lat_center":52.0,"lon_center":5.2,"detection_count":138,"mean_confidence":0.7172920525274414},{"lat_center":52.7,"lon_center":6.6,"detection_count":135,"mean_confidence":0.6747012897774025},{"lat_center":51.0,"lon_center":3.7,"detection_count":132,"mean_confidence":0.7992429794362098},{"lat_center":52.0,"lon_center":6.3,"detection_count":128,"mean_confidence":0.6617941935546696},{"lat_center":51.9,"lon_center":6.5,"detection_count":126,"mean_confidence":0.7366374035282741},{"lat_center":52.6,"lon_center":6.5,"detection_count":124,"mean_confidence":0.7566064745187759},{"lat_center":52.7,"lon_center":4.9,"detection_count":123,"mean_confidence":0.6535391851169307},{"lat_center":50.9,"lon_center":3.9,"detection_count":118,"mean_confidence":0.8055737288135593},{"lat_center":51.7,"lon_center":4.3,"detection_count":112,"mean_confidence":0.5223109501280955},{"lat_center":51.7,"lon_center":7.1,"detection_count":110,"mean_confidence":0.8156766940246929},{"lat_center":52.0,"lon_center":5.6,"detection_count":110,"mean_confidence":0.7243315020149405},{"lat_center":51.6,"lon_center":5.2,"detection_count":108,"mean_confidence":0.8117601851851852},{"lat_center":51.9,"lon_center":4.3,"detection_count":107,"mean_confidence":0.7819453996168119},{"lat_center":51.6,"lon_center":5.4,"detection_count":106,"mean_confidence":0.8018294719030272},{"lat_center":53.1,"lon_center":6.5,"detection_count":106,"mean_confidence":0.744767924528302},{"lat_center":52.3,"lon_center":6.2,"detection_count":102,"mean_confidence":0.7803503597932703},{"lat_center":52.7,"lon_center":4.8,"detection_count":102,"mean_confidence":0.6979021112942229},{"lat_center":53.1,"lon_center":7.0,"detection_count":102,"mean_confidence":0.8897063036759695},{"lat_center":52.3,"lon_center":5.6,"detection_count":101,"mean_confidence":0.8104059405940593},{"lat_center":51.9,"lon_center":4.6,"detection_count":100,"mean_confidence":0.5979516285657883},{"lat_center":52.2,"lon_center":5.8,"detection_count":98,"mean_confidence":0.7868744897959183},{"lat_center":51.3,"lon_center":5.3,"detection_count":92,"mean_confidence":0.8436695652173912},{"lat_center":51.1,"lon_center":7.1,"detection_count":90,"mean_confidence":0.9350955555555555},{"lat_center":51.6,"lon_center":4.8,"detection_count":84,"mean_confidence":0.699369314184643},{"lat_center":52.2,"lon_center":6.6,"detection_count":81,"mean_confidence":0.5344485544864043},{"lat_center":53.1,"lon_center":4.8,"detection_count":80,"mean_confidence":0.6742794498801231},{"lat_center":52.0,"lon_center":4.5,"detection_count":79,"mean_confidence":0.6635037170180792},{"lat_center":53.3,"lon_center":5.1,"detection_count":77,"mean_confidence":0.7904522287381159},{"lat_center":52.3,"lon_center":5.2,"detection_count":76,"mean_confidence":0.7338565980133257},{"lat_center":50.8,"lon_center":5.2,"detection_count":70,"mean_confidence":0.6241583611283984},{"lat_center":51.9,"lon_center":6.6,"detection_count":70,"mean_confidence":0.6382308257477624},{"lat_center":51.3,"lon_center":7.1,"detection_count":69,"mean_confidence":0.8738104554190151},{"lat_center":52.2,"lon_center":5.4,"detection_count":69,"mean_confidence":0.7085784167828768},{"lat_center":53.2,"lon_center":6.5,"detection_count":69,"mean_confidence":0.827867371831424},{"lat_center":52.2,"lon_center":5.9,"detection_count":68,"mean_confidence":0.7925514705882354},{"lat_center":53.1,"lon_center":6.3,"detection_count":65,"mean_confidence":0.9502384615384616},{"lat_center":53.4,"lon_center":6.4,"detection_count":64,"mean_confidence":0.4999715162746608},{"lat_center":51.1,"lon_center":4.2,"detection_count":61,"mean_confidence":0.8275253538225518},{"lat_center":51.2,"lon_center":7.0,"detection_count":61,"mean_confidence":0.7153880293252038},{"lat_center":52.1,"lon_center":6.2,"detection_count":61,"mean_confidence":0.5538866368473553},{"lat_center":53.3,"lon_center":6.1,"detection_count":61,"mean_confidence":0.7035262741026331},{"lat_center":51.2,"lon_center":6.8,"detection_count":59,"mean_confidence":0.8032159429081416},{"lat_center":52.0,"lon_center":6.4,"detection_count":58,"mean_confidence":0.8306758620689656},{"lat_center":51.7,"lon_center":3.9,"detection_count":56,"mean_confidence":0.6160798722079822},{"lat_center":52.4,"lon_center":6.1,"detection_count":56,"mean_confidence":0.6528267732688359},{"lat_center":53.4,"lon_center":6.8,"detection_count":55,"mean_confidence":0.8494641401550986},{"lat_center":53.1,"lon_center":6.4,"detection_count":53,"mean_confidence":0.7051879797341689},{"lat_center":52.0,"lon_center":4.6,"detection_count":52,"mean_confidence":0.6432698747286429},{"lat_center":53.2,"lon_center":6.9,"detection_count":49,"mean_confidence":0.8544300308032912},{"lat_center":51.2,"lon_center":6.0,"detection_count":48,"mean_confidence":0.6636222141484419},{"lat_center":51.4,"lon_center":5.6,"detection_count":48,"mean_confidence":0.8429604166666667},{"lat_center":53.0,"lon_center":6.3,"detection_count":48,"mean_confidence":0.9431916666666668},{"lat_center":51.5,"lon_center":6.0,"detection_count":47,"mean_confidence":0.872275710105896},{"lat_center":52.2,"lon_center":5.2,"detection_count":47,"mean_confidence":0.8714829787234042},{"lat_center":53.1,"lon_center":6.1,"detection_count":47,"mean_confidence":0.665245302192201},{"lat_center":53.2,"lon_center":6.2,"detection_count":47,"mean_confidence":0.8285468085106382},{"lat_center":51.2,"lon_center":4.3,"detection_count":46,"mean_confidence":0.824327738388725},{"lat_center":52.3,"lon_center":7.0,"detection_count":44,"mean_confidence":0.7983431818181818},{"lat_center":51.1,"lon_center":6.7,"detection_count":42,"mean_confidence":0.6629161565076738},{"lat_center":51.9,"lon_center":6.0,"detection_count":42,"mean_confidence":0.49214641395069303},{"lat_center":50.8,"lon_center":3.6,"detection_count":40,"mean_confidence":0.7926725},{"lat_center":52.4,"lon_center":5.1,"detection_count":40,"mean_confidence":0.7253475},{"lat_center":52.6,"lon_center":6.7,"detection_count":39,"mean_confidence":0.5812517205874125},{"lat_center":51.2,"lon_center":7.1,"detection_count":37,"mean_confidence":0.7925317641851064},{"lat_center":53.2,"lon_center":6.1,"detection_count":37,"mean_confidence":0.7213868547130275},{"lat_center":52.0,"lon_center":4.2,"detection_count":35,"mean_confidence":0.6810722324153355},{"lat_center":52.1,"lon_center":4.3,"detection_count":34,"mean_confidence":0.7693192987470066},{"lat_center":51.2,"lon_center":4.2,"detection_count":33,"mean_confidence":0.6499210559960568},{"lat_center":53.4,"lon_center":6.2,"detection_count":32,"mean_confidence":0.7276378087699413},{"lat_center":52.0,"lon_center":4.4,"detection_count":31,"mean_confidence":0.6592306033257516},{"lat_center":52.0,"lon_center":6.1,"detection_count":31,"mean_confidence":0.7872496729758478},{"lat_center":52.9,"lon_center":5.5,"detection_count":30,"mean_confidence":0.6748654375473658},{"lat_center":52.4,"lon_center":6.9,"detection_count":28,"mean_confidence":0.7897998648030418},{"lat_center":52.5,"lon_center":4.9,"detection_count":28,"mean_confidence":0.6974595657416752},{"lat_center":52.5,"lon_center":6.1,"detection_count":26,"mean_confidence":0.7933591643113356},{"lat_center":51.0,"lon_center":4.4,"detection_count":25,"mean_confidence":0.665661780834198},{"lat_center":51.0,"lon_center":6.4,"detection_count":25,"mean_confidence":0.9482295083999633},{"lat_center":51.1,"lon_center":4.7,"detection_count":25,"mean_confidence":0.8319277596473694},{"lat_center":52.4,"lon_center":4.6,"detection_count":25,"mean_confidence":0.7722852957248688},{"lat_center":52.5,"lon_center":6.2,"detection_count":25,"mean_confidence":0.88134},{"lat_center":52.8,"lon_center":6.9,"detection_count":25,"mean_confidence":0.622996723651886},{"lat_center":50.9,"lon_center":5.2,"detection_count":23,"mean_confidence":0.8964021050411722},{"lat_center":51.0,"lon_center":5.9,"detection_count":23,"mean_confidence":0.6654406760049902},{"lat_center":51.2,"lon_center":7.2,"detection_count":23,"mean_confidence":0.8139881595321323},{"lat_center":53.1,"lon_center":6.6,"detection_count":23,"mean_confidence":0.8542826086956521},{"lat_center":51.0,"lon_center":4.7,"detection_count":21,"mean_confidence":0.8883380952380953},{"lat_center":51.6,"lon_center":6.0,"detection_count":20,"mean_confidence":0.893},{"lat_center":52.4,"lon_center":5.8,"detection_count":20,"mean_confidence":0.8200863510370254},{"lat_center":50.8,"lon_center":4.0,"detection_count":19,"mean_confidence":0.889678947368421},{"lat_center":52.3,"lon_center":4.6,"detection_count":19,"mean_confidence":0.833576080046202},{"lat_center":51.2,"lon_center":4.6,"detection_count":18,"mean_confidence":0.9419791102409363},{"lat_center":51.2,"lon_center":6.7,"detection_count":18,"mean_confidence":0.7492117981115977},{"lat_center":51.9,"lon_center":4.5,"detection_count":17,"mean_confidence":0.7744588235294119},{"lat_center":50.9,"lon_center":4.6,"detection_count":16,"mean_confidence":0.8908649533987045},{"lat_center":51.6,"lon_center":5.3,"detection_count":16,"mean_confidence":0.8566703163087368},{"lat_center":52.3,"lon_center":4.7,"detection_count":16,"mean_confidence":0.7619896754622459},{"lat_center":51.0,"lon_center":4.6,"detection_count":15,"mean_confidence":0.8915266666666667},{"lat_center":51.8,"lon_center":5.8,"detection_count":15,"mean_confidence":0.9299999999999999},{"lat_center":51.6,"lon_center":4.6,"detection_count":14,"mean_confidence":0.6214192467076438},{"lat_center":51.9,"lon_center":4.4,"detection_count":14,"mean_confidence":0.7798285714285714},{"lat_center":51.9,"lon_center":5.8,"detection_count":14,"mean_confidence":0.6553385768617902},{"lat_center":51.4,"lon_center":6.8,"detection_count":13,"mean_confidence":0.7961538461538461},{"lat_center":50.8,"lon_center":7.2,"detection_count":11,"mean_confidence":0.897690909090909},{"lat_center":51.6,"lon_center":7.2,"detection_count":11,"mean_confidence":0.600366470488635},{"lat_center":52.1,"lon_center":5.0,"detection_count":11,"mean_confidence":0.8461181818181818},{"lat_center":52.2,"lon_center":4.4,"detection_count":11,"mean_confidence":0.8795799558812921},{"lat_center":50.9,"lon_center":3.5,"detection_count":10,"mean_confidence":0.6787340760231018},{"lat_center":53.2,"lon_center":5.8,"detection_count":10,"mean_confidence":0.7463559768009186},{"lat_center":51.1,"lon_center":4.9,"detection_count":9,"mean_confidence":0.6701342066129049},{"lat_center":52.3,"lon_center":6.5,"detection_count":9,"mean_confidence":0.6177444444444444},{"lat_center":53.0,"lon_center":5.4,"detection_count":9,"mean_confidence":0.7977777777777777},{"lat_center":51.9,"lon_center":5.5,"detection_count":8,"mean_confidence":0.6758534610271454},{"lat_center":52.0,"lon_center":5.3,"detection_count":8,"mean_confidence":0.8558125},{"lat_center":52.1,"lon_center":4.5,"detection_count":8,"mean_confidence":0.786675},{"lat_center":50.9,"lon_center":3.8,"detection_count":7,"mean_confidence":0.5697887539863586},{"lat_center":51.0,"lon_center":5.8,"detection_count":7,"mean_confidence":0.8085714285714286},{"lat_center":51.1,"lon_center":3.7,"detection_count":7,"mean_confidence":0.8241142857142857},{"lat_center":52.0,"lon_center":4.3,"detection_count":7,"mean_confidence":0.8151428571428571},{"lat_center":52.7,"lon_center":6.8,"detection_count":7,"mean_confidence":0.9245571428571429},{"lat_center":53.2,"lon_center":5.7,"detection_count":7,"mean_confidence":0.8619},{"lat_center":53.4,"lon_center":6.6,"detection_count":7,"mean_confidence":0.835980338709695},{"lat_center":50.9,"lon_center":4.2,"detection_count":6,"mean_confidence":0.7883166666666667},{"lat_center":51.1,"lon_center":5.7,"detection_count":6,"mean_confidence":0.8983333333333333},{"lat_center":53.1,"lon_center":6.7,"detection_count":6,"mean_confidence":0.6416060030460358},{"lat_center":51.5,"lon_center":3.9,"detection_count":5,"mean_confidence":0.8199799999999999},{"lat_center":51.5,"lon_center":6.2,"detection_count":5,"mean_confidence":0.8973800000000001},{"lat_center":52.3,"lon_center":5.0,"detection_count":5,"mean_confidence":0.83446},{"lat_center":51.6,"lon_center":5.9,"detection_count":4,"mean_confidence":0.8623800128698349},{"lat_center":51.7,"lon_center":3.7,"detection_count":4,"mean_confidence":0.8335864543914795},{"lat_center":51.8,"lon_center":4.6,"detection_count":4,"mean_confidence":0.5399626716971397},{"lat_center":52.1,"lon_center":5.5,"detection_count":4,"mean_confidence":0.875},{"lat_center":52.2,"lon_center":6.0,"detection_count":4,"mean_confidence":0.773675},{"lat_center":52.7,"lon_center":6.4,"detection_count":4,"mean_confidence":0.8952596187591553},{"lat_center":52.9,"lon_center":7.0,"detection_count":4,"mean_confidence":0.7949999999999999},{"lat_center":51.5,"lon_center":5.1,"detection_count":3,"mean_confidence":0.8966666666666666},{"lat_center":51.9,"lon_center":5.0,"detection_count":3,"mean_confidence":0.8104191422462463},{"lat_center":52.1,"lon_center":4.7,"detection_count":3,"mean_confidence":0.4712657332420349},{"lat_center":52.2,"lon_center":6.5,"detection_count":3,"mean_confidence":0.6459472974141439},{"lat_center":52.5,"lon_center":4.8,"detection_count":3,"mean_confidence":0.8342999999999999},{"lat_center":52.9,"lon_center":5.9,"detection_count":3,"mean_confidence":0.7983758846918741},{"lat_center":53.2,"lon_center":6.7,"detection_count":3,"mean_confidence":0.6413931647936503},{"lat_center":50.9,"lon_center":6.0,"detection_count":2,"mean_confidence":0.895},{"lat_center":50.9,"lon_center":6.4,"detection_count":2,"mean_confidence":0.5301978141069412},{"lat_center":51.2,"lon_center":3.6,"detection_count":2,"mean_confidence":0.7354499999999999},{"lat_center":51.2,"lon_center":5.0,"detection_count":2,"mean_confidence":0.8888499999999999},{"lat_center":51.3,"lon_center":3.9,"detection_count":2,"mean_confidence":0.7415499999999999},{"lat_center":51.6,"lon_center":6.7,"detection_count":2,"mean_confidence":0.6497722268104553},{"lat_center":51.9,"lon_center":5.9,"detection_count":2,"mean_confidence":0.7425227457523346},{"lat_center":52.5,"lon_center":4.6,"detection_count":2,"mean_confidence":0.6110890209674835},{"lat_center":52.5,"lon_center":6.4,"detection_count":2,"mean_confidence":0.576723575592041},{"lat_center":53.0,"lon_center":5.9,"detection_count":2,"mean_confidence":0.8354559540748596},{"lat_center":53.2,"lon_center":6.3,"detection_count":2,"mean_confidence":0.7362},{"lat_center":53.3,"lon_center":6.5,"detection_count":2,"mean_confidence":0.7832919955253601},{"lat_center":50.9,"lon_center":5.6,"detection_count":1,"mean_confidence":0.98},{"lat_center":51.5,"lon_center":5.6,"detection_count":1,"mean_confidence":0.9028207659721375},{"lat_center":51.8,"lon_center":5.7,"detection_count":1,"mean_confidence":0.8828501105308533},{"lat_center":52.0,"lon_center":5.1,"detection_count":1,"mean_confidence":0.7084094882011414},{"lat_center":52.6,"lon_center":6.3,"detection_count":1,"mean_confidence":0.7337},{"lat_center":52.8,"lon_center":6.7,"detection_count":1,"mean_confidence":0.8860673904418945},{"lat_center":52.9,"lon_center":5.0,"detection_count":1,"mean_confidence":0.8930278420448303},{"lat_center":53.4,"lon_center":5.3,"detection_count":1,"mean_confidence":0.7490820288658142}]