[{"lat_center":51.5,"lon_center":3.6,"detection_count":62,"mean_confidence":0.5536779578654997},{"lat_center":52.1,"lon_center":4.5,"detection_count":57,"mean_confidence":0.7789805404763472},{"lat_center":50.9,"lon_center":4.7,"detection_count":51,"mean_confidence":0.7437876229192696},{"lat_center":52.2,"lon_center":5.1,"detection_count":26,"mean_confidence":0.7924423076923077},{"lat_center":52.2,"lon_center":4.5,"detection_count":24,"mean_confidence":0.547169907639424},{"lat_center":52.2,"lon_center":6.5,"detection_count":22,"mean_confidence":0.724636205218055},{"lat_center":52.0,"lon_center":5.7,"detection_count":12,"mean_confidence":0.61408864458402},{"lat_center":52.2,"lon_center":5.0,"detection_count":12,"mean_confidence":0.8327749999999999},{"lat_center":52.2,"lon_center":5.5,"detection_count":11,"mean_confidence":0.6143249110742048},{"lat_center":51.7,"lon_center":4.3,"detection_count":9,"mean_confidence":0.533747222688463},{"lat_center":52.1,"lon_center":5.2,"detection_count":8,"mean_confidence":0.8463375},{"lat_center":52.2,"lon_center":6.6,"detection_count":8,"mean_confidence":0.48359979689121246},{"lat_center":52.4,"lon_center":6.5,"detection_count":8,"mean_confidence":0.4856649674475193},{"lat_center":52.0,"lon_center":4.6,"detection_count":7,"mean_confidence":0.9166995201792035},{"lat_center":52.0,"lon_center":5.2,"detection_count":6,"mean_confidence":0.7023864289124807},{"lat_center":52.2,"lon_center":4.6,"detection_count":6,"mean_confidence":0.8268006716666667},{"lat_center":53.0,"lon_center":4.8,"detection_count":5,"mean_confidence":0.795598944},{"lat_center":53.1,"lon_center":6.4,"detection_count":5,"mean_confidence":0.6809903979301453},{"lat_center":51.5,"lon_center":4.1,"detection_count":2,"mean_confidence":0.72565},{"lat_center":51.7,"lon_center":5.0,"detection_count":2,"mean_confidence":0.5264789164066315},{"lat_center":51.7,"lon_center":6.0,"detection_count":2,"mean_confidence":0.7037999629974365},{"lat_center":52.0,"lon_center":5.6,"detection_count":2,"mean_confidence":0.7774694263935089},{"lat_center":52.6,"lon_center":6.7,"detection_count":2,"mean_confidence":0.4355672299861908},{"lat_center":51.0,"lon_center":3.9,"detection_count":1,"mean_confidence":0.7555967569351196},{"lat_center":51.0,"lon_center":4.4,"detection_count":1,"mean_confidence":0.5836184024810791},{"lat_center":51.2,"lon_center":4.2,"detection_count":1,"mean_confidence":0.5614253878593445},{"lat_center":51.3,"lon_center":5.6,"detection_count":1,"mean_confidence":0.7555597424507141},{"lat_center":51.6,"lon_center":4.0,"detection_count":1,"mean_confidence":0.7450965642929077},{"lat_center":51.6,"lon_center":4.7,"detection_count":1,"mean_confidence":0.8020272254943848},{"lat_center":51.8,"lon_center":4.6,"detection_count":1,"mean_confidence":0.6353476643562317},{"lat_center":51.8,"lon_center":5.8,"detection_count":1,"mean_confidence":0.8165},{"lat_center":51.9,"lon_center":4.1,"detection_count":1,"mean_confidence":0.4063911736011505},{"lat_center":52.0,"lon_center":4.8,"detection_count":1,"mean_confidence":0.8166428208351135},{"lat_center":52.0,"lon_center":6.4,"detection_count":1,"mean_confidence":0.7334},{"lat_center":52.1,"lon_center":5.0,"detection_count":1,"mean_confidence":0.741},{"lat_center":52.1,"lon_center":6.3,"detection_count":1,"mean_confidence":0.5923608541488647},{"lat_center":52.2,"lon_center":5.6,"detection_count":1,"mean_confidence":0.6668272614479065},{"lat_center":52.3,"lon_center":4.6,"detection_count":1,"mean_confidence":0.5199016332626343},{"lat_center":52.4,"lon_center":4.6,"detection_count":1,"mean_confidence":0.414539098739624},{"lat_center":53.4,"lon_center":5.6,"detection_count":1,"mean_confidence":0.47884926199913025}]