[{"lat_center":51.6,"lon_center":3.7,"detection_count":6077,"mean_confidence":0.9225765141743234},{"lat_center":50.9,"lon_center":3.4,"detection_count":241,"mean_confidence":0.6945820015495744},{"lat_center":50.9,"lon_center":5.3,"detection_count":241,"mean_confidence":0.8459975981712341},{"lat_center":51.4,"lon_center":4.5,"detection_count":166,"mean_confidence":0.6578747019710312},{"lat_center":50.8,"lon_center":5.2,"detection_count":71,"mean_confidence":0.6659525582488154},{"lat_center":52.1,"lon_center":5.1,"detection_count":65,"mean_confidence":0.6363606948118944},{"lat_center":51.0,"lon_center":6.4,"detection_count":64,"mean_confidence":0.9447363950312138},{"lat_center":51.9,"lon_center":6.5,"detection_count":56,"mean_confidence":0.7612330520221164},{"lat_center":50.9,"lon_center":3.6,"detection_count":55,"mean_confidence":0.6563546039841391},{"lat_center":51.5,"lon_center":4.9,"detection_count":54,"mean_confidence":0.6268909396948638},{"lat_center":52.4,"lon_center":6.9,"detection_count":52,"mean_confidence":0.6230778258580428},{"lat_center":51.7,"lon_center":4.3,"detection_count":42,"mean_confidence":0.6854884596098036},{"lat_center":51.4,"lon_center":5.5,"detection_count":41,"mean_confidence":0.6591050057876401},{"lat_center":52.4,"lon_center":6.5,"detection_count":38,"mean_confidence":0.6331864734975915},{"lat_center":50.9,"lon_center":3.7,"detection_count":37,"mean_confidence":0.6426382048709972},{"lat_center":52.6,"lon_center":6.7,"detection_count":37,"mean_confidence":0.5219020634084135},{"lat_center":52.0,"lon_center":5.6,"detection_count":36,"mean_confidence":0.7397576984432008},{"lat_center":52.8,"lon_center":6.9,"detection_count":34,"mean_confidence":0.6618333406308118},{"lat_center":51.7,"lon_center":3.9,"detection_count":32,"mean_confidence":0.6731458026915789},{"lat_center":52.0,"lon_center":6.4,"detection_count":28,"mean_confidence":0.8125357142857144},{"lat_center":50.9,"lon_center":3.8,"detection_count":27,"mean_confidence":0.536844731480987},{"lat_center":52.2,"lon_center":5.5,"detection_count":27,"mean_confidence":0.6899658353240402},{"lat_center":52.7,"lon_center":4.9,"detection_count":27,"mean_confidence":0.6709159060760781},{"lat_center":51.1,"lon_center":4.3,"detection_count":25,"mean_confidence":0.7648167085647583},{"lat_center":51.9,"lon_center":6.6,"detection_count":25,"mean_confidence":0.5127690124511719},{"lat_center":50.9,"lon_center":4.8,"detection_count":24,"mean_confidence":0.803771992524465},{"lat_center":52.1,"lon_center":6.5,"detection_count":21,"mean_confidence":0.7304042266709464},{"lat_center":51.2,"lon_center":4.2,"detection_count":20,"mean_confidence":0.6393082678318024},{"lat_center":52.6,"lon_center":6.3,"detection_count":19,"mean_confidence":0.8180741131578948},{"lat_center":52.1,"lon_center":4.3,"detection_count":17,"mean_confidence":0.7208175386518052},{"lat_center":52.4,"lon_center":4.6,"detection_count":16,"mean_confidence":0.6988474242389202},{"lat_center":50.8,"lon_center":4.0,"detection_count":14,"mean_confidence":0.821636452279772},{"lat_center":51.9,"lon_center":4.1,"detection_count":14,"mean_confidence":0.5212101297719138},{"lat_center":52.2,"lon_center":5.3,"detection_count":13,"mean_confidence":0.6969973330173551},{"lat_center":52.4,"lon_center":5.8,"detection_count":13,"mean_confidence":0.7829443445572486},{"lat_center":51.2,"lon_center":3.6,"detection_count":12,"mean_confidence":0.7552083333333334},{"lat_center":51.6,"lon_center":5.5,"detection_count":12,"mean_confidence":0.5100376183787981},{"lat_center":52.0,"lon_center":5.8,"detection_count":12,"mean_confidence":0.5307061995069186},{"lat_center":51.9,"lon_center":5.3,"detection_count":11,"mean_confidence":0.5265029831366106},{"lat_center":52.0,"lon_center":5.2,"detection_count":11,"mean_confidence":0.6728211478753523},{"lat_center":52.7,"lon_center":4.7,"detection_count":11,"mean_confidence":0.5750652903860266},{"lat_center":50.9,"lon_center":4.6,"detection_count":10,"mean_confidence":0.7825342416763306},{"lat_center":51.5,"lon_center":3.6,"detection_count":10,"mean_confidence":0.6426795065402985},{"lat_center":52.0,"lon_center":4.4,"detection_count":10,"mean_confidence":0.654463529586792},{"lat_center":52.3,"lon_center":5.3,"detection_count":10,"mean_confidence":0.6244322240352631},{"lat_center":53.3,"lon_center":5.1,"detection_count":10,"mean_confidence":0.6969119489192963},{"lat_center":50.9,"lon_center":7.1,"detection_count":9,"mean_confidence":0.8409349422222222},{"lat_center":52.0,"lon_center":4.2,"detection_count":9,"mean_confidence":0.7809222222222222},{"lat_center":52.1,"lon_center":6.3,"detection_count":9,"mean_confidence":0.6908548143174913},{"lat_center":53.1,"lon_center":6.4,"detection_count":9,"mean_confidence":0.652668469481998},{"lat_center":52.0,"lon_center":4.8,"detection_count":8,"mean_confidence":0.6623731777071953},{"lat_center":52.2,"lon_center":4.6,"detection_count":8,"mean_confidence":0.75274212375},{"lat_center":52.3,"lon_center":5.6,"detection_count":8,"mean_confidence":0.788},{"lat_center":50.8,"lon_center":3.6,"detection_count":7,"mean_confidence":0.7943999999999999},{"lat_center":51.1,"lon_center":5.6,"detection_count":7,"mean_confidence":0.8121999999999999},{"lat_center":51.2,"lon_center":7.1,"detection_count":7,"mean_confidence":0.6714407801628113},{"lat_center":50.9,"lon_center":4.7,"detection_count":6,"mean_confidence":0.7523692150910696},{"lat_center":51.6,"lon_center":7.2,"detection_count":6,"mean_confidence":0.5533395161231359},{"lat_center":51.8,"lon_center":5.7,"detection_count":6,"mean_confidence":0.8201741127173107},{"lat_center":51.8,"lon_center":5.9,"detection_count":6,"mean_confidence":0.6556264360745748},{"lat_center":51.9,"lon_center":5.8,"detection_count":6,"mean_confidence":0.6522139310836792},{"lat_center":52.1,"lon_center":6.4,"detection_count":6,"mean_confidence":0.7143877347310384},{"lat_center":52.9,"lon_center":5.9,"detection_count":6,"mean_confidence":0.8473599950472513},{"lat_center":51.0,"lon_center":3.7,"detection_count":5,"mean_confidence":0.7284619409179688},{"lat_center":51.0,"lon_center":4.4,"detection_count":5,"mean_confidence":0.6584282398223877},{"lat_center":51.5,"lon_center":5.6,"detection_count":5,"mean_confidence":0.79410325050354},{"lat_center":52.2,"lon_center":5.7,"detection_count":5,"mean_confidence":0.8463357925415039},{"lat_center":52.9,"lon_center":5.0,"detection_count":5,"mean_confidence":0.6847301840782165},{"lat_center":51.2,"lon_center":7.0,"detection_count":4,"mean_confidence":0.7443743795156479},{"lat_center":51.3,"lon_center":5.4,"detection_count":4,"mean_confidence":0.765575},{"lat_center":51.6,"lon_center":5.9,"detection_count":4,"mean_confidence":0.6196824461221695},{"lat_center":52.0,"lon_center":4.5,"detection_count":4,"mean_confidence":0.6154501587152481},{"lat_center":52.8,"lon_center":5.0,"detection_count":4,"mean_confidence":0.5844446569681168},{"lat_center":53.4,"lon_center":6.4,"detection_count":4,"mean_confidence":0.6416305303573608},{"lat_center":51.2,"lon_center":4.6,"detection_count":3,"mean_confidence":0.932039221127828},{"lat_center":51.2,"lon_center":4.9,"detection_count":3,"mean_confidence":0.6089607874552408},{"lat_center":52.0,"lon_center":4.6,"detection_count":3,"mean_confidence":0.5628335475921631},{"lat_center":52.2,"lon_center":4.9,"detection_count":3,"mean_confidence":0.8725785811742147},{"lat_center":52.2,"lon_center":5.4,"detection_count":3,"mean_confidence":0.7631525198618571},{"lat_center":52.2,"lon_center":6.6,"detection_count":3,"mean_confidence":0.43587077657381695},{"lat_center":53.3,"lon_center":6.4,"detection_count":3,"mean_confidence":0.7666000000000001},{"lat_center":50.8,"lon_center":3.5,"detection_count":2,"mean_confidence":0.828201775},{"lat_center":50.8,"lon_center":5.7,"detection_count":2,"mean_confidence":0.90392366},{"lat_center":51.1,"lon_center":4.2,"detection_count":2,"mean_confidence":0.7954641878604889},{"lat_center":51.1,"lon_center":4.5,"detection_count":2,"mean_confidence":0.7171850502490997},{"lat_center":51.1,"lon_center":7.0,"detection_count":2,"mean_confidence":0.76835},{"lat_center":51.3,"lon_center":4.5,"detection_count":2,"mean_confidence":0.7154958844184875},{"lat_center":51.3,"lon_center":7.1,"detection_count":2,"mean_confidence":0.8372761607170105},{"lat_center":51.5,"lon_center":4.5,"detection_count":2,"mean_confidence":0.5864643454551697},{"lat_center":51.8,"lon_center":4.6,"detection_count":2,"mean_confidence":0.4884439557790756},{"lat_center":51.8,"lon_center":6.7,"detection_count":2,"mean_confidence":0.81440548},{"lat_center":51.9,"lon_center":5.9,"detection_count":2,"mean_confidence":0.6335706684589386},{"lat_center":52.0,"lon_center":5.0,"detection_count":2,"mean_confidence":0.5778409540653229},{"lat_center":52.1,"lon_center":4.7,"detection_count":2,"mean_confidence":0.6045806556940079},{"lat_center":52.1,"lon_center":5.2,"detection_count":2,"mean_confidence":0.920104056596756},{"lat_center":52.3,"lon_center":6.2,"detection_count":2,"mean_confidence":0.5438200533390045},{"lat_center":52.7,"lon_center":4.8,"detection_count":2,"mean_confidence":0.76745},{"lat_center":53.2,"lon_center":5.7,"detection_count":2,"mean_confidence":0.74418992},{"lat_center":53.2,"lon_center":6.0,"detection_count":2,"mean_confidence":0.6682588458061218},{"lat_center":50.8,"lon_center":4.3,"detection_count":1,"mean_confidence":0.7670846},{"lat_center":50.8,"lon_center":6.1,"detection_count":1,"mean_confidence":0.8015989},{"lat_center":50.8,"lon_center":7.1,"detection_count":1,"mean_confidence":0.7287551164627075},{"lat_center":50.9,"lon_center":5.7,"detection_count":1,"mean_confidence":0.8846882581710815},{"lat_center":51.0,"lon_center":4.5,"detection_count":1,"mean_confidence":0.5542},{"lat_center":51.0,"lon_center":4.6,"detection_count":1,"mean_confidence":0.8893},{"lat_center":51.1,"lon_center":4.1,"detection_count":1,"mean_confidence":0.93},{"lat_center":51.1,"lon_center":4.9,"detection_count":1,"mean_confidence":0.6963098049163818},{"lat_center":51.1,"lon_center":6.7,"detection_count":1,"mean_confidence":0.55176842212677},{"lat_center":51.2,"lon_center":4.1,"detection_count":1,"mean_confidence":0.9},{"lat_center":51.2,"lon_center":6.7,"detection_count":1,"mean_confidence":0.560964822769165},{"lat_center":51.3,"lon_center":5.3,"detection_count":1,"mean_confidence":0.7135},{"lat_center":51.4,"lon_center":6.4,"detection_count":1,"mean_confidence":0.8387},{"lat_center":51.6,"lon_center":4.7,"detection_count":1,"mean_confidence":0.6094356179237366},{"lat_center":51.6,"lon_center":5.6,"detection_count":1,"mean_confidence":0.6021593809127808},{"lat_center":51.7,"lon_center":3.7,"detection_count":1,"mean_confidence":0.9520987868309021},{"lat_center":51.7,"lon_center":5.3,"detection_count":1,"mean_confidence":0.7735231518745422},{"lat_center":51.8,"lon_center":7.2,"detection_count":1,"mean_confidence":0.7320676},{"lat_center":51.9,"lon_center":4.3,"detection_count":1,"mean_confidence":0.7126},{"lat_center":52.0,"lon_center":4.7,"detection_count":1,"mean_confidence":0.6940940618515015},{"lat_center":52.0,"lon_center":5.7,"detection_count":1,"mean_confidence":0.805455207824707},{"lat_center":52.1,"lon_center":5.0,"detection_count":1,"mean_confidence":0.7777},{"lat_center":52.1,"lon_center":6.2,"detection_count":1,"mean_confidence":0.6662134528160095},{"lat_center":52.2,"lon_center":4.5,"detection_count":1,"mean_confidence":0.6268934011459351},{"lat_center":52.2,"lon_center":6.0,"detection_count":1,"mean_confidence":0.7775},{"lat_center":52.2,"lon_center":6.1,"detection_count":1,"mean_confidence":0.52109694480896},{"lat_center":52.3,"lon_center":4.6,"detection_count":1,"mean_confidence":0.8952253460884094},{"lat_center":52.4,"lon_center":4.9,"detection_count":1,"mean_confidence":0.9239376187324524},{"lat_center":53.1,"lon_center":6.6,"detection_count":1,"mean_confidence":0.9516238570213318},{"lat_center":53.2,"lon_center":6.5,"detection_count":1,"mean_confidence":0.8083}]