[{"lat_center":52.2,"lon_center":6.1,"detection_count":813,"mean_confidence":0.6150824266312893},{"lat_center":52.9,"lon_center":5.5,"detection_count":503,"mean_confidence":0.6212521920621277},{"lat_center":52.4,"lon_center":4.6,"detection_count":302,"mean_confidence":0.5261639429638717},{"lat_center":52.0,"lon_center":5.2,"detection_count":49,"mean_confidence":0.6852705570473963},{"lat_center":51.8,"lon_center":5.9,"detection_count":24,"mean_confidence":0.6298564523458481},{"lat_center":50.9,"lon_center":3.9,"detection_count":21,"mean_confidence":0.8035428571428572},{"lat_center":53.4,"lon_center":6.4,"detection_count":14,"mean_confidence":0.4741214285714285},{"lat_center":52.4,"lon_center":6.5,"detection_count":13,"mean_confidence":0.702838821873298},{"lat_center":51.8,"lon_center":4.7,"detection_count":10,"mean_confidence":0.48011560142040255},{"lat_center":53.1,"lon_center":6.3,"detection_count":10,"mean_confidence":0.97578},{"lat_center":53.0,"lon_center":6.3,"detection_count":8,"mean_confidence":0.953175},{"lat_center":52.2,"lon_center":5.4,"detection_count":7,"mean_confidence":0.8247448716844831},{"lat_center":53.2,"lon_center":5.8,"detection_count":7,"mean_confidence":0.9606},{"lat_center":52.0,"lon_center":5.6,"detection_count":5,"mean_confidence":0.842639612197876},{"lat_center":52.7,"lon_center":4.7,"detection_count":5,"mean_confidence":0.8044841561508178},{"lat_center":53.1,"lon_center":6.1,"detection_count":5,"mean_confidence":0.8825155973434449},{"lat_center":53.1,"lon_center":6.9,"detection_count":5,"mean_confidence":0.87568},{"lat_center":50.9,"lon_center":4.7,"detection_count":4,"mean_confidence":0.6426005065441132},{"lat_center":51.4,"lon_center":5.5,"detection_count":4,"mean_confidence":0.5525899529457092},{"lat_center":51.5,"lon_center":3.6,"detection_count":4,"mean_confidence":0.908003106713295},{"lat_center":51.5,"lon_center":4.5,"detection_count":4,"mean_confidence":0.8467332869768143},{"lat_center":51.9,"lon_center":6.0,"detection_count":4,"mean_confidence":0.6644292622804642},{"lat_center":52.0,"lon_center":5.7,"detection_count":4,"mean_confidence":0.6081777364015579},{"lat_center":52.4,"lon_center":6.0,"detection_count":4,"mean_confidence":0.932125},{"lat_center":52.5,"lon_center":6.1,"detection_count":4,"mean_confidence":0.9157},{"lat_center":51.5,"lon_center":5.5,"detection_count":3,"mean_confidence":0.7426666666666666},{"lat_center":51.8,"lon_center":4.8,"detection_count":3,"mean_confidence":0.8552188674608866},{"lat_center":52.2,"lon_center":6.5,"detection_count":3,"mean_confidence":0.6452283461888632},{"lat_center":52.3,"lon_center":5.3,"detection_count":3,"mean_confidence":0.677338977654775},{"lat_center":52.6,"lon_center":6.5,"detection_count":3,"mean_confidence":0.7715582648913065},{"lat_center":53.1,"lon_center":6.4,"detection_count":3,"mean_confidence":0.7787055174509684},{"lat_center":50.9,"lon_center":3.4,"detection_count":2,"mean_confidence":0.5402160286903381},{"lat_center":50.9,"lon_center":5.7,"detection_count":2,"mean_confidence":0.83075},{"lat_center":51.5,"lon_center":5.6,"detection_count":2,"mean_confidence":0.73275},{"lat_center":51.9,"lon_center":4.4,"detection_count":2,"mean_confidence":0.8021},{"lat_center":51.9,"lon_center":5.9,"detection_count":2,"mean_confidence":0.7398},{"lat_center":52.0,"lon_center":4.6,"detection_count":2,"mean_confidence":0.6678843200206757},{"lat_center":52.0,"lon_center":4.8,"detection_count":2,"mean_confidence":0.8153806328773499},{"lat_center":52.2,"lon_center":4.5,"detection_count":2,"mean_confidence":0.8378854990005493},{"lat_center":52.2,"lon_center":6.6,"detection_count":2,"mean_confidence":0.4804396331310272},{"lat_center":52.3,"lon_center":4.7,"detection_count":2,"mean_confidence":0.6564662754535675},{"lat_center":52.3,"lon_center":6.8,"detection_count":2,"mean_confidence":0.8268500000000001},{"lat_center":53.0,"lon_center":5.4,"detection_count":2,"mean_confidence":0.9},{"lat_center":53.1,"lon_center":6.6,"detection_count":2,"mean_confidence":0.7369116544723511},{"lat_center":53.2,"lon_center":6.0,"detection_count":2,"mean_confidence":0.7033559679985046},{"lat_center":53.2,"lon_center":6.9,"detection_count":2,"mean_confidence":0.9159533977508545},{"lat_center":50.8,"lon_center":5.7,"detection_count":1,"mean_confidence":0.76},{"lat_center":50.8,"lon_center":7.2,"detection_count":1,"mean_confidence":0.9411},{"lat_center":50.9,"lon_center":3.5,"detection_count":1,"mean_confidence":0.7996681332588196},{"lat_center":50.9,"lon_center":4.2,"detection_count":1,"mean_confidence":0.7444},{"lat_center":51.0,"lon_center":3.7,"detection_count":1,"mean_confidence":0.8122},{"lat_center":51.0,"lon_center":4.4,"detection_count":1,"mean_confidence":0.507047176361084},{"lat_center":51.1,"lon_center":3.7,"detection_count":1,"mean_confidence":0.8982},{"lat_center":51.2,"lon_center":6.7,"detection_count":1,"mean_confidence":0.5869520306587219},{"lat_center":51.4,"lon_center":5.6,"detection_count":1,"mean_confidence":0.9062},{"lat_center":51.4,"lon_center":6.9,"detection_count":1,"mean_confidence":0.6138773560523987},{"lat_center":51.7,"lon_center":3.7,"detection_count":1,"mean_confidence":0.774320662021637},{"lat_center":51.8,"lon_center":4.6,"detection_count":1,"mean_confidence":0.6219121217727661},{"lat_center":51.9,"lon_center":4.8,"detection_count":1,"mean_confidence":0.780551016330719},{"lat_center":52.0,"lon_center":5.1,"detection_count":1,"mean_confidence":0.7368},{"lat_center":52.1,"lon_center":4.3,"detection_count":1,"mean_confidence":0.6263289451599121},{"lat_center":52.1,"lon_center":4.7,"detection_count":1,"mean_confidence":0.4120163321495056},{"lat_center":52.1,"lon_center":5.5,"detection_count":1,"mean_confidence":0.82},{"lat_center":52.2,"lon_center":6.9,"detection_count":1,"mean_confidence":0.9477},{"lat_center":52.3,"lon_center":5.6,"detection_count":1,"mean_confidence":0.7858},{"lat_center":52.3,"lon_center":6.2,"detection_count":1,"mean_confidence":0.6587681770324707},{"lat_center":52.4,"lon_center":5.1,"detection_count":1,"mean_confidence":0.5507},{"lat_center":52.5,"lon_center":4.8,"detection_count":1,"mean_confidence":0.9024},{"lat_center":52.6,"lon_center":6.7,"detection_count":1,"mean_confidence":0.4216526746749878},{"lat_center":52.9,"lon_center":6.3,"detection_count":1,"mean_confidence":0.6468602418899536},{"lat_center":53.2,"lon_center":6.1,"detection_count":1,"mean_confidence":0.563726544380188},{"lat_center":53.2,"lon_center":6.6,"detection_count":1,"mean_confidence":0.8969622254371643},{"lat_center":53.4,"lon_center":6.6,"detection_count":1,"mean_confidence":0.38828393816947937}]